{"url": "https://api.github.com/repos/bytecodealliance/userfaultfd-rs/pulls/25", "id": 754809799, "node_id": "PR_kwDODrgh_c4s_XvH", "html_url": "https://github.com/bytecodealliance/userfaultfd-rs/pull/25", "diff_url": "https://github.com/bytecodealliance/userfaultfd-rs/pull/25.diff", "patch_url": "https://github.com/bytecodealliance/userfaultfd-rs/pull/25.patch", "issue_url": "https://api.github.com/repos/bytecodealliance/userfaultfd-rs/issues/25", "number": 25, "state": "closed", "locked": false, "title": "update `nix` dependency to 0.23, bump package to 0.4.1", "user": {"login": "pchickey", "id": 118618, "node_id": "MDQ6VXNlcjExODYxOA==", "avatar_url": "https://avatars.githubusercontent.com/u/118618?v=4", "gravatar_id": "", "url": "https://api.github.com/users/pchickey", "html_url": "https://github.com/pchickey", "followers_url": "https://api.github.com/users/pchickey/followers", "following_url": "https://api.github.com/users/pchickey/following{/other_user}", "gists_url": "https://api.github.com/users/pchickey/gists{/gist_id}", "starred_url": "https://api.github.com/users/pchickey/starred{/owner}{/repo}", "subscriptions_url": "https://api.github.com/users/pchickey/subscriptions", "organizations_url": "https://api.github.com/users/pchickey/orgs", "repos_url": "https://api.github.com/users/pchickey/repos", "events_url": "https://api.github.com/users/pchickey/events{/privacy}", "received_events_url": "https://api.github.com/users/pchickey/received_events", "type": "User", "user_view_type": "public", "site_admin": false}, "body": "There is a RUSTSEC advisory on `nix 0.17`. Although it does not appear that `userfaultfd` is vulnerable to this defect, this PR updates `nix` to the latest `0.23`, and bumps the userfaultfd package version to `0.4.1`\r\n\r\n\r\nexample `cargo audit` output:\r\n```\r\nerror: 1 vulnerability found!\r\nCrate:         nix\r\nVersion:       0.17.0\r\nTitle:         Out-of-bounds write in nix::unistd::getgrouplist\r\nDate:          2021-09-27\r\nID:            RUSTSEC-2021-0119\r\nURL:           https://rustsec.org/advisories/RUSTSEC-2021-0119\r\nSolution:      Upgrade to ^0.20.2 OR ^0.21.2 OR ^0.22.2 OR >=0.23.0\r\n```", "created_at": "2021-10-11T00:12:03Z", "updated_at": "2021-10-11T17:23:20Z", "closed_at": "2021-10-11T17:21:58Z", "merged_at": "2021-10-11T17:21:58Z", "merge_commit_sha": "a3c6fbf67e3cf81724482a4c6815eba57608eb1d", "assignee": null, "assignees": [], "requested_reviewers": [], "requested_teams": [], "labels": [], "milestone": null, "draft": false, "commits_url": "https://api.github.com/repos/bytecodealliance/userfaultfd-rs/pulls/25/commits", "review_comments_url": "https://api.github.com/repos/bytecodealliance/userfaultfd-rs/pulls/25/comments", "review_comment_url": "https://api.github.com/repos/bytecodealliance/userfaultfd-rs/pulls/comments{/number}", "comments_url": "https://api.github.com/repos/bytecodealliance/userfaultfd-rs/issues/25/comments", "statuses_url": "https://api.github.com/repos/bytecodealliance/userfaultfd-rs/statuses/c1889569ce1876db2c0c1b787384e348ee1f10fd", "head": {"label": "bytecodealliance:pch/0.4.1", "ref": "pch/0.4.1", "sha": "c1889569ce1876db2c0c1b787384e348ee1f10fd", "user": {"login": "bytecodealliance", "id": 54038801, "node_id": "MDEyOk9yZ2FuaXphdGlvbjU0MDM4ODAx", "avatar_url": "https://avatars.githubusercontent.com/u/54038801?v=4", "gravatar_id": "", "url": "https://api.github.com/users/bytecodealliance", "html_url": "https://github.com/bytecodealliance", "followers_url": "https://api.github.com/users/bytecodealliance/followers", "following_url": "https://api.github.com/users/bytecodealliance/following{/other_user}", "gists_url": "https://api.github.com/users/bytecodealliance/gists{/gist_id}", "starred_url": "https://api.github.com/users/bytecodealliance/starred{/owner}{/repo}", "subscriptions_url": "https://api.github.com/users/bytecodealliance/subscriptions", "organizations_url": "https://api.github.com/users/bytecodealliance/orgs", "repos_url": "https://api.github.com/users/bytecodealliance/repos", "events_url": "https://api.github.com/users/bytecodealliance/events{/privacy}", "received_events_url": "https://api.github.com/users/bytecodealliance/received_events", "type": "Organization", "user_view_type": "public", "site_admin": false}, "repo": {"id": 246948349, "node_id": "MDEwOlJlcG9zaXRvcnkyNDY5NDgzNDk=", "name": "userfaultfd-rs", "full_name": "bytecodealliance/userfaultfd-rs", "private": false, "owner": {"login": "bytecodealliance", "id": 54038801, "node_id": "MDEyOk9yZ2FuaXphdGlvbjU0MDM4ODAx", "avatar_url": "https://avatars.githubusercontent.com/u/54038801?v=4", "gravatar_id": "", "url": "https://api.github.com/users/bytecodealliance", "html_url": "https://github.com/bytecodealliance", "followers_url": "https://api.github.com/users/bytecodealliance/followers", "following_url": "https://api.github.com/users/bytecodealliance/following{/other_user}", "gists_url": "https://api.github.com/users/bytecodealliance/gists{/gist_id}", "starred_url": "https://api.github.com/users/bytecodealliance/starred{/owner}{/repo}", "subscriptions_url": "https://api.github.com/users/bytecodealliance/subscriptions", "organizations_url": "https://api.github.com/users/bytecodealliance/orgs", "repos_url": "https://api.github.com/users/bytecodealliance/repos", "events_url": "https://api.github.com/users/bytecodealliance/events{/privacy}", "received_events_url": "https://api.github.com/users/bytecodealliance/received_events", "type": "Organization", "user_view_type": "public", "site_admin": false}, "html_url": "https://github.com/bytecodealliance/userfaultfd-rs", "description": "Rust bindings for the Linux userfaultfd functionality", "fork": false, "url": "https://api.github.com/repos/bytecodealliance/userfaultfd-rs", "forks_url": "https://api.github.com/repos/bytecodealliance/userfaultfd-rs/forks", "keys_url": "https://api.github.com/repos/bytecodealliance/userfaultfd-rs/keys{/key_id}", "collaborators_url": "https://api.github.com/repos/bytecodealliance/userfaultfd-rs/collaborators{/collaborator}", "teams_url": "https://api.github.com/repos/bytecodealliance/userfaultfd-rs/teams", "hooks_url": "https://api.github.com/repos/bytecodealliance/userfaultfd-rs/hooks", "issue_events_url": "https://api.github.com/repos/bytecodealliance/userfaultfd-rs/issues/events{/number}", "events_url": "https://api.github.com/repos/bytecodealliance/userfaultfd-rs/events", "assignees_url": "https://api.github.com/repos/bytecodealliance/userfaultfd-rs/assignees{/user}", "branches_url": "https://api.github.com/repos/bytecodealliance/userfaultfd-rs/branches{/branch}", "tags_url": "https://api.github.com/repos/bytecodealliance/userfaultfd-rs/tags", "blobs_url": "https://api.github.com/repos/bytecodealliance/userfaultfd-rs/git/blobs{/sha}", "git_tags_url": "https://api.github.com/repos/bytecodealliance/userfaultfd-rs/git/tags{/sha}", "git_refs_url": "https://api.github.com/repos/bytecodealliance/userfaultfd-rs/git/refs{/sha}", "trees_url": "https://api.github.com/repos/bytecodealliance/userfaultfd-rs/git/trees{/sha}", "statuses_url": "https://api.github.com/repos/bytecodealliance/userfaultfd-rs/statuses/{sha}", "languages_url": "https://api.github.com/repos/bytecodealliance/userfaultfd-rs/languages", "stargazers_url": "https://api.github.com/repos/bytecodealliance/userfaultfd-rs/stargazers", "contributors_url": "https://api.github.com/repos/bytecodealliance/userfaultfd-rs/contributors", "subscribers_url": "https://api.github.com/repos/bytecodealliance/userfaultfd-rs/subscribers", "subscription_url": "https://api.github.com/repos/bytecodealliance/userfaultfd-rs/subscription", "commits_url": "https://api.github.com/repos/bytecodealliance/userfaultfd-rs/commits{/sha}", "git_commits_url": "https://api.github.com/repos/bytecodealliance/userfaultfd-rs/git/commits{/sha}", "comments_url": "https://api.github.com/repos/bytecodealliance/userfaultfd-rs/comments{/number}", "issue_comment_url": "https://api.github.com/repos/bytecodealliance/userfaultfd-rs/issues/comments{/number}", "contents_url": "https://api.github.com/repos/bytecodealliance/userfaultfd-rs/contents/{+path}", "compare_url": "https://api.github.com/repos/bytecodealliance/userfaultfd-rs/compare/{base}...{head}", "merges_url": "https://api.github.com/repos/bytecodealliance/userfaultfd-rs/merges", "archive_url": "https://api.github.com/repos/bytecodealliance/userfaultfd-rs/{archive_format}{/ref}", "downloads_url": "https://api.github.com/repos/bytecodealliance/userfaultfd-rs/downloads", "issues_url": "https://api.github.com/repos/bytecodealliance/userfaultfd-rs/issues{/number}", "pulls_url": "https://api.github.com/repos/bytecodealliance/userfaultfd-rs/pulls{/number}", "milestones_url": "https://api.github.com/repos/bytecodealliance/userfaultfd-rs/milestones{/number}", "notifications_url": "https://api.github.com/repos/bytecodealliance/userfaultfd-rs/notifications{?since,all,participating}", "labels_url": "https://api.github.com/repos/bytecodealliance/userfaultfd-rs/labels{/name}", "releases_url": "https://api.github.com/repos/bytecodealliance/userfaultfd-rs/releases{/id}", "deployments_url": "https://api.github.com/repos/bytecodealliance/userfaultfd-rs/deployments", "created_at": "2020-03-12T23:24:04Z", "updated_at": "2025-11-22T17:42:52Z", "pushed_at": "2026-01-19T00:50:53Z", "git_url": "git://github.com/bytecodealliance/userfaultfd-rs.git", "ssh_url": "git@github.com:bytecodealliance/userfaultfd-rs.git", "clone_url": "https://github.com/bytecodealliance/userfaultfd-rs.git", "svn_url": "https://github.com/bytecodealliance/userfaultfd-rs", "homepage": null, "size": 128, "stargazers_count": 46, "watchers_count": 46, "language": "Rust", "has_issues": true, "has_projects": true, "has_downloads": true, "has_wiki": true, "has_pages": false, "has_discussions": false, "forks_count": 28, "mirror_url": null, "archived": false, "disabled": false, "open_issues_count": 11, "license": {"key": "apache-2.0", "name": "Apache License 2.0", "spdx_id": "Apache-2.0", "url": "https://api.github.com/licenses/apache-2.0", "node_id": "MDc6TGljZW5zZTI="}, "allow_forking": true, "is_template": false, "web_commit_signoff_required": false, "topics": [], "visibility": "public", "forks": 28, "open_issues": 11, "watchers": 46, "default_branch": "main"}}, "base": {"label": "bytecodealliance:main", "ref": "main", "sha": "4caa25141c5d98333b865d8b3281fb04253c4fa0", "user": {"login": "bytecodealliance", "id": 54038801, "node_id": "MDEyOk9yZ2FuaXphdGlvbjU0MDM4ODAx", "avatar_url": "https://avatars.githubusercontent.com/u/54038801?v=4", "gravatar_id": "", "url": "https://api.github.com/users/bytecodealliance", "html_url": "https://github.com/bytecodealliance", "followers_url": "https://api.github.com/users/bytecodealliance/followers", "following_url": "https://api.github.com/users/bytecodealliance/following{/other_user}", "gists_url": "https://api.github.com/users/bytecodealliance/gists{/gist_id}", "starred_url": "https://api.github.com/users/bytecodealliance/starred{/owner}{/repo}", "subscriptions_url": "https://api.github.com/users/bytecodealliance/subscriptions", "organizations_url": "https://api.github.com/users/bytecodealliance/orgs", "repos_url": "https://api.github.com/users/bytecodealliance/repos", "events_url": "https://api.github.com/users/bytecodealliance/events{/privacy}", "received_events_url": "https://api.github.com/users/bytecodealliance/received_events", "type": "Organization", "user_view_type": "public", "site_admin": false}, "repo": {"id": 246948349, "node_id": "MDEwOlJlcG9zaXRvcnkyNDY5NDgzNDk=", "name": "userfaultfd-rs", "full_name": "bytecodealliance/userfaultfd-rs", "private": false, "owner": {"login": "bytecodealliance", "id": 54038801, "node_id": "MDEyOk9yZ2FuaXphdGlvbjU0MDM4ODAx", "avatar_url": "https://avatars.githubusercontent.com/u/54038801?v=4", "gravatar_id": "", "url": "https://api.github.com/users/bytecodealliance", "html_url": "https://github.com/bytecodealliance", "followers_url": "https://api.github.com/users/bytecodealliance/followers", "following_url": "https://api.github.com/users/bytecodealliance/following{/other_user}", "gists_url": "https://api.github.com/users/bytecodealliance/gists{/gist_id}", "starred_url": "https://api.github.com/users/bytecodealliance/starred{/owner}{/repo}", "subscriptions_url": "https://api.github.com/users/bytecodealliance/subscriptions", "organizations_url": "https://api.github.com/users/bytecodealliance/orgs", "repos_url": "https://api.github.com/users/bytecodealliance/repos", "events_url": "https://api.github.com/users/bytecodealliance/events{/privacy}", "received_events_url": "https://api.github.com/users/bytecodealliance/received_events", "type": "Organization", "user_view_type": "public", "site_admin": false}, "html_url": "https://github.com/bytecodealliance/userfaultfd-rs", "description": "Rust bindings for the Linux userfaultfd functionality", "fork": false, "url": "https://api.github.com/repos/bytecodealliance/userfaultfd-rs", "forks_url": "https://api.github.com/repos/bytecodealliance/userfaultfd-rs/forks", "keys_url": "https://api.github.com/repos/bytecodealliance/userfaultfd-rs/keys{/key_id}", "collaborators_url": "https://api.github.com/repos/bytecodealliance/userfaultfd-rs/collaborators{/collaborator}", "teams_url": "https://api.github.com/repos/bytecodealliance/userfaultfd-rs/teams", "hooks_url": "https://api.github.com/repos/bytecodealliance/userfaultfd-rs/hooks", "issue_events_url": "https://api.github.com/repos/bytecodealliance/userfaultfd-rs/issues/events{/number}", "events_url": "https://api.github.com/repos/bytecodealliance/userfaultfd-rs/events", "assignees_url": "https://api.github.com/repos/bytecodealliance/userfaultfd-rs/assignees{/user}", "branches_url": "https://api.github.com/repos/bytecodealliance/userfaultfd-rs/branches{/branch}", "tags_url": "https://api.github.com/repos/bytecodealliance/userfaultfd-rs/tags", "blobs_url": "https://api.github.com/repos/bytecodealliance/userfaultfd-rs/git/blobs{/sha}", "git_tags_url": "https://api.github.com/repos/bytecodealliance/userfaultfd-rs/git/tags{/sha}", "git_refs_url": "https://api.github.com/repos/bytecodealliance/userfaultfd-rs/git/refs{/sha}", "trees_url": "https://api.github.com/repos/bytecodealliance/userfaultfd-rs/git/trees{/sha}", "statuses_url": "https://api.github.com/repos/bytecodealliance/userfaultfd-rs/statuses/{sha}", "languages_url": "https://api.github.com/repos/bytecodealliance/userfaultfd-rs/languages", "stargazers_url": "https://api.github.com/repos/bytecodealliance/userfaultfd-rs/stargazers", "contributors_url": "https://api.github.com/repos/bytecodealliance/userfaultfd-rs/contributors", "subscribers_url": "https://api.github.com/repos/bytecodealliance/userfaultfd-rs/subscribers", "subscription_url": "https://api.github.com/repos/bytecodealliance/userfaultfd-rs/subscription", "commits_url": "https://api.github.com/repos/bytecodealliance/userfaultfd-rs/commits{/sha}", "git_commits_url": "https://api.github.com/repos/bytecodealliance/userfaultfd-rs/git/commits{/sha}", "comments_url": "https://api.github.com/repos/bytecodealliance/userfaultfd-rs/comments{/number}", "issue_comment_url": "https://api.github.com/repos/bytecodealliance/userfaultfd-rs/issues/comments{/number}", "contents_url": "https://api.github.com/repos/bytecodealliance/userfaultfd-rs/contents/{+path}", "compare_url": "https://api.github.com/repos/bytecodealliance/userfaultfd-rs/compare/{base}...{head}", "merges_url": "https://api.github.com/repos/bytecodealliance/userfaultfd-rs/merges", "archive_url": "https://api.github.com/repos/bytecodealliance/userfaultfd-rs/{archive_format}{/ref}", "downloads_url": "https://api.github.com/repos/bytecodealliance/userfaultfd-rs/downloads", "issues_url": "https://api.github.com/repos/bytecodealliance/userfaultfd-rs/issues{/number}", "pulls_url": "https://api.github.com/repos/bytecodealliance/userfaultfd-rs/pulls{/number}", "milestones_url": "https://api.github.com/repos/bytecodealliance/userfaultfd-rs/milestones{/number}", "notifications_url": "https://api.github.com/repos/bytecodealliance/userfaultfd-rs/notifications{?since,all,participating}", "labels_url": "https://api.github.com/repos/bytecodealliance/userfaultfd-rs/labels{/name}", "releases_url": "https://api.github.com/repos/bytecodealliance/userfaultfd-rs/releases{/id}", "deployments_url": "https://api.github.com/repos/bytecodealliance/userfaultfd-rs/deployments", "created_at": "2020-03-12T23:24:04Z", "updated_at": "2025-11-22T17:42:52Z", "pushed_at": "2026-01-19T00:50:53Z", "git_url": "git://github.com/bytecodealliance/userfaultfd-rs.git", "ssh_url": "git@github.com:bytecodealliance/userfaultfd-rs.git", "clone_url": "https://github.com/bytecodealliance/userfaultfd-rs.git", "svn_url": "https://github.com/bytecodealliance/userfaultfd-rs", "homepage": null, "size": 128, "stargazers_count": 46, "watchers_count": 46, "language": "Rust", "has_issues": true, "has_projects": true, "has_downloads": true, "has_wiki": true, "has_pages": false, "has_discussions": false, "forks_count": 28, "mirror_url": null, "archived": false, "disabled": false, "open_issues_count": 11, "license": {"key": "apache-2.0", "name": "Apache License 2.0", "spdx_id": "Apache-2.0", "url": "https://api.github.com/licenses/apache-2.0", "node_id": "MDc6TGljZW5zZTI="}, "allow_forking": true, "is_template": false, "web_commit_signoff_required": false, "topics": [], "visibility": "public", "forks": 28, "open_issues": 11, "watchers": 46, "default_branch": "main"}}, "_links": {"self": {"href": "https://api.github.com/repos/bytecodealliance/userfaultfd-rs/pulls/25"}, "html": {"href": "https://github.com/bytecodealliance/userfaultfd-rs/pull/25"}, "issue": {"href": "https://api.github.com/repos/bytecodealliance/userfaultfd-rs/issues/25"}, "comments": {"href": "https://api.github.com/repos/bytecodealliance/userfaultfd-rs/issues/25/comments"}, "review_comments": {"href": "https://api.github.com/repos/bytecodealliance/userfaultfd-rs/pulls/25/comments"}, "review_comment": {"href": "https://api.github.com/repos/bytecodealliance/userfaultfd-rs/pulls/comments{/number}"}, "commits": {"href": "https://api.github.com/repos/bytecodealliance/userfaultfd-rs/pulls/25/commits"}, "statuses": {"href": "https://api.github.com/repos/bytecodealliance/userfaultfd-rs/statuses/c1889569ce1876db2c0c1b787384e348ee1f10fd"}}, "author_association": "COLLABORATOR", "auto_merge": null, "active_lock_reason": null, "merged": true, "mergeable": null, "rebaseable": null, "mergeable_state": "unknown", "merged_by": {"login": "pchickey", "id": 118618, "node_id": "MDQ6VXNlcjExODYxOA==", "avatar_url": "https://avatars.githubusercontent.com/u/118618?v=4", "gravatar_id": "", "url": "https://api.github.com/users/pchickey", "html_url": "https://github.com/pchickey", "followers_url": "https://api.github.com/users/pchickey/followers", "following_url": "https://api.github.com/users/pchickey/following{/other_user}", "gists_url": "https://api.github.com/users/pchickey/gists{/gist_id}", "starred_url": "https://api.github.com/users/pchickey/starred{/owner}{/repo}", "subscriptions_url": "https://api.github.com/users/pchickey/subscriptions", "organizations_url": "https://api.github.com/users/pchickey/orgs", "repos_url": "https://api.github.com/users/pchickey/repos", "events_url": "https://api.github.com/users/pchickey/events{/privacy}", "received_events_url": "https://api.github.com/users/pchickey/received_events", "type": "User", "user_view_type": "public", "site_admin": false}, "comments": 0, "review_comments": 0, "maintainer_can_modify": false, "commits": 2, "additions": 19, "deletions": 33, "changed_files": 3}